<?xml version="1.0" encoding="utf-8" ?>
<dwsync>
<file name="itemMall.css" server="218.234.20.171//lunaplus_re/" local="129203624263417500" remote="129203623800000000" />
<file name="index.php" server="mu3.nayana.kr//html/" local="129479570963287410" remote="129479571000000000" />
<file name="itBox.php" server="mu3.nayana.kr//html/" local="129479528292426777" remote="129479528400000000" />
<file name="itemBuyCom.php" server="mu3.nayana.kr//html/" local="129479528292906804" remote="129479528400000000" />
<file name="itemBuyPop.php" server="mu3.nayana.kr//html/" local="129479528292996809" remote="129479528400000000" />
<file name="itemCtn.php" server="mu3.nayana.kr//html/" local="129479528293146818" remote="129479528400000000" />
<file name="itemList.php" server="mu3.nayana.kr//html/" local="129479528338089388" remote="129479528400000000" />
<file name="itemMall.css" server="mu3.nayana.kr//html/" local="129479578217202311" remote="129479577600000000" />
<file name="itemPop.php" server="mu3.nayana.kr//html/" local="129479528295616959" remote="129479528400000000" />
<file name="itemSch.php" server="mu3.nayana.kr//html/" local="129479528295656961" remote="129479528400000000" />
<file name="itemSpecPop.php" server="mu3.nayana.kr//html/" local="129479528295716965" remote="129479528400000000" />
<file name="itemTop.php" server="mu3.nayana.kr//html/" local="129479570350872382" remote="129479569800000000" />
<file name="leftMenu.php" server="mu3.nayana.kr//html/" local="129479528296076985" remote="129479528400000000" />
<file name="paging.php" server="mu3.nayana.kr//html/" local="129479528296236995" remote="129479528400000000" />
<file name="rollBanner.php" server="mu3.nayana.kr//html/" local="129479528296276997" remote="129479528400000000" />
</dwsync>